mbridge/__init__.py
mbridge/core/__init__.py
mbridge/core/auto_bridge.py
mbridge/core/bridge.py
mbridge/core/llm_bridge.py
mbridge/core/parallel_states.py
mbridge/core/safetensor_io.py
mbridge/core/util.py
mbridge/core/vlm_bridge.py
mbridge/models/__init__.py
mbridge/models/deepseek_v3.py
mbridge/models/glm4moe.py
mbridge/models/llama.py
mbridge/models/mimo.py
mbridge/models/mixtral.py
mbridge/models/qwen2.py
mbridge/models/qwen2moe.py
mbridge/models/qwen3.py
mbridge/models/qwen3moe.py
mbridge/models/ext/deepseek_v3/dequant_fp8_safetensor_io.py
mbridge/models/ext/deepseek_v3/kernel.py
mbridge/models/ext/llama3_cp/cp_utils.py
mbridge/models/ext/llama3_cp/llama3_cp_memory_efficient_attention.py
mbridge/models/gemma3/__init__.py
mbridge/models/gemma3/gpt_model.py
mbridge/models/gemma3/model.py
mbridge/models/gemma3/projector.py
mbridge/models/gemma3/transformer_config.py
mbridge/models/gemma3/transformer_layer.py
mbridge/models/glm4_vl/__init__.py
mbridge/models/glm4_vl/base_bridge.py
mbridge/models/glm4_vl/model.py
mbridge/models/glm4_vl/transformer_config.py
mbridge/models/glm4_vl/transformer_layer.py
mbridge/models/glm4_vl/vl_mixin.py
mbridge/models/glm4_vl/inference/__init__.py
mbridge/models/glm4_vl/inference/inference_request.py
mbridge/models/glm4_vl/inference/model_inference_controller.py
mbridge/models/glm4_vl/inference/model_inference_warpper.py
mbridge/models/internvl3/__init__.py
mbridge/models/internvl3/internvl_vit_model.py
mbridge/models/internvl3/model.py
mbridge/models/internvl3/transformer_config.py
mbridge/models/internvl3/transformer_layer.py
mbridge/models/qwen2_5_vl/__init__.py
mbridge/models/qwen2_5_vl/attention.py
mbridge/models/qwen2_5_vl/model.py
mbridge/models/qwen2_5_vl/rope_utils.py
mbridge/models/qwen2_5_vl/transformer_config.py
mbridge/models/qwen2_5_vl/vision_model.py
mbridge/models/qwen2_5_vl/vision_transformer_block.py
mbridge/utils/__init__.py
mbridge/utils/layer.py
mbridge/utils/mappings.py
mbridge/utils/post_creation_callbacks.py
mbridge-0.15.1.dist-info/licenses/LICENSE
mbridge-0.15.1.dist-info/METADATA
mbridge-0.15.1.dist-info/WHEEL
mbridge-0.15.1.dist-info/top_level.txt
mbridge-0.15.1.dist-info/RECORD
