Metadata-Version: 2.4
Name: mbridge
Version: 0.15.1
Summary: Bridge Megatron-Core to Hugging Face/Reinforcement Learning
Author-email: Yan Bai <bayan@nvidia.com>
License-Expression: Apache-2.0
Project-URL: Homepage, https://github.com/ISEEKYAN/mbridge
Project-URL: Bug Tracker, https://github.com/ISEEKYAN/mbridge/issues
Requires-Python: >=3.8
License-File: LICENSE
Provides-Extra: megatron
Requires-Dist: megatron-core>=0.12.0; extra == "megatron"
Requires-Dist: transformers; extra == "megatron"
Requires-Dist: safetensors; extra == "megatron"
Requires-Dist: einops; extra == "megatron"
Provides-Extra: test
Requires-Dist: pytest; extra == "test"
Dynamic: license-file
